cloakrt/README.md
cloakrt/__init__.py
cloakrt/analyze_eval_awareness.py
cloakrt/batch_runner.py
cloakrt/cli.py
cloakrt/competition.py
cloakrt/detector.py
cloakrt/harmony.py
cloakrt/model_interface.py
cloakrt/ollama_model.py
cloakrt/requirements.txt
cloakrt/response_validator.py
cloakrt/runners.py
cloakrt/schema.py
cloakrt/scoring.py
cloakrt/semantic_harm.py
cloakrt/setup.py
cloakrt/probes/__init__.py
cloakrt/probes/base.py
cloakrt/probes/chain_of_thought.py
cloakrt/probes/data_exfiltration.py
cloakrt/probes/deception.py
cloakrt/probes/evaluation_awareness.py
cloakrt/probes/hidden_motivations.py
cloakrt/probes/inappropriate_tool_use.py
cloakrt/probes/reward_hacking.py
cloakrt/probes/sabotage.py
cloakrt/probes/sandbagging.py
cloakrt/tests/__init__.py
cloakrt/tests/test_imports.py
cloakrt-0.1.0.dist-info/licenses/LICENSE
cloakrt-0.1.0.dist-info/METADATA
cloakrt-0.1.0.dist-info/WHEEL
cloakrt-0.1.0.dist-info/entry_points.txt
cloakrt-0.1.0.dist-info/top_level.txt
cloakrt-0.1.0.dist-info/RECORD
