Metadata-Version: 2.4
Name: cloakrt
Version: 0.1.0
Summary: Framing-first red-teaming for LLMs
Home-page: https://github.com/hartmantexas/cloakrt
Author: Adam Hartman
Author-email: Adam Hartman <pixeldrift00@gmail.com>
License: MIT
Project-URL: Homepage, https://github.com/hartmantexas/cloakrt
Project-URL: Repository, https://github.com/hartmantexas/cloakrt.git
Classifier: Development Status :: 4 - Beta
Classifier: Intended Audience :: Science/Research
Classifier: Topic :: Security
Classifier: Topic :: Scientific/Engineering :: Artificial Intelligence
Classifier: License :: OSI Approved :: MIT License
Classifier: Programming Language :: Python :: 3
Classifier: Programming Language :: Python :: 3.8
Classifier: Programming Language :: Python :: 3.9
Classifier: Programming Language :: Python :: 3.10
Classifier: Programming Language :: Python :: 3.11
Classifier: Operating System :: OS Independent
Requires-Python: >=3.8
License-File: LICENSE
Requires-Dist: pyyaml>=6.0
Requires-Dist: requests>=2.31.0
Requires-Dist: python-dotenv>=1.0.0
Provides-Extra: dev
Requires-Dist: pytest>=7.4.0; extra == "dev"
Requires-Dist: pytest-cov>=4.1.0; extra == "dev"
Requires-Dist: black>=23.0.0; extra == "dev"
Requires-Dist: flake8>=6.0.0; extra == "dev"
Requires-Dist: mypy>=1.5.0; extra == "dev"
Provides-Extra: ml
Requires-Dist: torch>=2.0.0; extra == "ml"
Requires-Dist: transformers>=4.35.0; extra == "ml"
Requires-Dist: numpy>=1.24.0; extra == "ml"
Dynamic: author
Dynamic: home-page
Dynamic: license-file
Dynamic: requires-python
